brain_dump/__init__.py
brain_dump/cli/__init__.py
brain_dump/cli/graphviz_md2png.py
brain_dump/cli/wisemapping_md2xml.py
brain_dump/cli/wisemapping_wxml2xml.py
brain_dump/graphviz.py
brain_dump/parsers/__init__.py
brain_dump/parsers/indented_text_graph.py
brain_dump/parsers/pseudo_markdown.py
brain_dump/twilio_webhook_gitdb_app.py
brain_dump/wisemapping_xml.py
brain_dump-1.1.5.dist-info/entry_points.txt
brain_dump-1.1.5.dist-info/LICENSE.txt
brain_dump-1.1.5.dist-info/WHEEL
brain_dump-1.1.5.dist-info/METADATA
brain_dump-1.1.5.dist-info/RECORD
