Metadata-Version: 2.1
Name: brain-dump
Version: 1.1.5
Summary: Tools to generate mindmaps compatible from markdown-like text files, either as PNG with graphviz or as wisemapping-compatible XMLs
Home-page: http://github.com/Lucas-C/brain_dump
License: GPL-3.0
Keywords: mindmap,graph,markdown,graphviz,parser
Author: Lucas Cimon
Requires-Python: >=3.6,<4.0
Classifier: License :: OSI Approved :: GNU General Public License v3 (GPLv3)
Classifier: Programming Language :: Python :: 3
Classifier: Programming Language :: Python :: 3.6
Classifier: Programming Language :: Python :: 3.7
Requires-Dist: pydot
Requires-Dist: pyparsing
Project-URL: Repository, http://github.com/Lucas-C/brain_dump
